sockeye/__init__.py
sockeye/arguments.py
sockeye/average.py
sockeye/beam_search.py
sockeye/checkpoint_decoder.py
sockeye/config.py
sockeye/constants.py
sockeye/convert_deepspeed.py
sockeye/data_io.py
sockeye/decoder.py
sockeye/embeddings.py
sockeye/encoder.py
sockeye/evaluate.py
sockeye/generate_decoder_states.py
sockeye/git_version.py
sockeye/inference.py
sockeye/initial_setup.py
sockeye/knn.py
sockeye/layers.py
sockeye/lexicon.py
sockeye/log.py
sockeye/loss.py
sockeye/lr_scheduler.py
sockeye/model.py
sockeye/nvs.py
sockeye/optimizers.py
sockeye/output_handler.py
sockeye/prepare_data.py
sockeye/quantize.py
sockeye/rerank.py
sockeye/score.py
sockeye/scoring.py
sockeye/test_utils.py
sockeye/train.py
sockeye/training.py
sockeye/transformer.py
sockeye/translate.py
sockeye/utils.py
sockeye/vocab.py
sockeye_contrib/__init__.py
sockeye_contrib/plot_metrics.py
sockeye_contrib/rouge.py
sockeye-3.1.34.dist-info/LICENSE
sockeye-3.1.34.dist-info/METADATA
sockeye-3.1.34.dist-info/NOTICE
sockeye-3.1.34.dist-info/WHEEL
sockeye-3.1.34.dist-info/entry_points.txt
sockeye-3.1.34.dist-info/top_level.txt
sockeye-3.1.34.dist-info/RECORD
