Metadata-Version: 2.1
Name: sockeye
Version: 3.1.34
Summary: Sequence-to-Sequence framework for Neural Machine Translation
Home-page: https://github.com/awslabs/sockeye
Author: Amazon
Author-email: sockeye-dev@amazon.com
Maintainer-email: sockeye-dev@amazon.com
License: Apache License 2.0
Platform: UNKNOWN
Classifier: License :: OSI Approved :: Apache Software License
Classifier: Programming Language :: Python :: 3 :: Only
Requires-Python: >=3
Requires-Dist: torch (<1.14.0,>=1.10.0)
Requires-Dist: pyyaml (>=5.1)
Requires-Dist: numpy (<2.0.0,>1.16.0)
Requires-Dist: sacrebleu (>=2.3.0)
Provides-Extra: dev
Requires-Dist: pytest ; extra == 'dev'
Requires-Dist: pytest-cov (<2.6.0) ; extra == 'dev'
Requires-Dist: pillow ; extra == 'dev'
Requires-Dist: check-manifest ; extra == 'dev'
Requires-Dist: matplotlib ; extra == 'dev'
Requires-Dist: mypy (==0.790) ; extra == 'dev'
Requires-Dist: pylint (==2.6.0) ; extra == 'dev'
Requires-Dist: isort (<5.0.0) ; extra == 'dev'
Requires-Dist: setuptools (>=38.6.0) ; extra == 'dev'
Requires-Dist: twine (>=1.11.0) ; extra == 'dev'
Requires-Dist: wheel (>=0.31.0) ; extra == 'dev'
Provides-Extra: optional
Requires-Dist: tensorboard ; extra == 'optional'
Requires-Dist: matplotlib ; extra == 'optional'
